{
    "1091264685": {
        "data": false
    },
    "1106749203": {
        "data": false
    },
    "1254338201": {
        "data": false
    },
    "1528770791": {
        "data": false
    },
    "100032212041503": {
        "data": true
    },
    "5000797103320307": {
        "data": false
    },
    "4839966469384117": {
        "data": false
    },
    "5096282627102524": {
        "data": true
    },
    "4265186810273355": {
        "data": true
    },
    "5047631608637397": {
        "data": false
    },
    "4946855372034295": {
        "data": false
    },
    "4987478761345273": {
        "data": false
    },
    "5212578228799737": {
        "data": false
    },
    "7397254016983505": {
        "data": false
    },
    "4736168856436174": {
        "data": false
    },
    "5304583592919650": {
        "data": false
    },
    "4517711528327718": {
        "data": false
    },
    "4829344277188636": {
        "data": false
    },
    "100056953105174": {
        "data": false
    },
    "100057162087212": {
        "data": false
    },
    "100060780590589": {
        "data": false
    },
    "100072401748027": {
        "data": false
    },
    "100049395483074": {
        "data": false
    },
    "4216423178460610": {
        "data": false
    },
    "4916767025023465": {
        "data": false
    },
    "5108429732510613": {
        "data": false
    },
    "5366146830084731": {
        "data": false
    },
    "5168853156500094": {
        "data": false
    },
    "5093468500709704": {
        "data": false
    },
    "100041184706360": {
        "data": false
    },
    "4917079548360478": {
        "data": false
    },
    "4843503235719525": {
        "data": false
    },
    "6787029071369988": {
        "data": false
    },
    "100079715251584": {
        "data": false
    },
    "6925910700783694": {
        "data": false
    },
    "100046745231201": {
        "data": false
    },
    "7195743817165212": {
        "data": false
    },
    "3940556452732431": {
        "data": false
    },
    "100063050334248": {
        "data": false
    },
    "100077902491098": {
        "data": false
    },
    "5107363619301831": {
        "data": false
    },
    "100070082857127": {
        "data": false
    },
    "100061891156986": {
        "data": false
    },
    "7205476452855737": {
        "data": false
    },
    "100025361627541": {
        "data": false
    },
    "4866311396755606": {
        "data": false
    },
    "100070308248142": {
        "data": false
    },
    "100068774907051": {
        "data": false
    },
    "100072834392720": {
        "data": false
    },
    "100077355639846": {
        "data": false
    },
    "5208690202503786": {
        "data": false
    },
    "4560503990735568": {
        "data": false
    },
    "100049162717191": {
        "data": false
    },
    "100068504695009": {
        "data": false
    },
    "3562163113908274": {
        "data": false
    },
    "4709449182498984": {
        "data": false
    },
    "4831831540198511": {
        "data": false
    },
    "100042965476833": {
        "data": false
    },
    "4863930113694524": {
        "data": false
    },
    "4671196582984559": {
        "data": false
    },
    "100001615478510": {
        "data": false
    },
    "5071393366271206": {
        "data": false
    },
    "4701605556589591": {
        "data": false
    },
    "100034418953237": {
        "data": false
    },
    "100014811933322": {
        "data": false
    },
    "4963533557058382": {
        "data": false
    },
    "5054573317920255": {
        "data": false
    },
    "4847575521994535": {
        "data": false
    },
    "4275176359267338": {
        "data": false
    },
    "5030828633636438": {
        "data": false
    },
    "7642903905727452": {
        "data": false
    },
    "4732438443526818": {
        "data": false
    },
    "4663840980388430": {
        "data": true
    },
    "4838810452862952": {
        "data": false
    },
    "100080476939874": {
        "data": false
    },
    "100054491144010": {
        "data": false
    },
    "100074156839173": {
        "data": false
    },
    "4879813532139328": {
        "data": false
    },
    "4501455469907965": {
        "data": false
    },
    "4682331811844285": {
        "data": false
    },
    "100045361870603": {
        "data": false
    },
    "100075201728678": {
        "data": false
    },
    "7259331644108200": {
        "data": false
    },
    "100073252547292": {
        "data": false
    },
    "5074324459277712": {
        "data": false
    },
    "5182503108437341": {
        "data": false
    },
    "4880922078683833": {
        "data": true
    },
    "100018185582351": {
        "data": false
    },
    "5643501992330730": {
        "data": false
    },
    "100010810517331": {
        "data": false
    },
    "100075403052412": {
        "data": false
    },
    "5031208906963934": {
        "data": false
    },
    "7488656374540368": {
        "data": false
    },
    "100012199992153": {
        "data": false
    },
    "5265163443520918": {
        "data": false
    },
    "5033784543325140": {
        "data": false
    },
    "5333664166683969": {
        "data": false
    },
    "100057997731920": {
        "data": false
    },
    "100065670395858": {
        "data": false
    },
    "5010518475732575": {
        "data": false
    },
    "100048505611574": {
        "data": false
    },
    "100024470479155": {
        "data": false
    },
    "100015382905072": {
        "data": false
    },
    "4943036409148396": {
        "data": false
    },
    "4582026905211778": {
        "data": false
    },
    "4584775691621156": {
        "data": false
    },
    "5226846607350832": {
        "data": false
    },
    "4263916343708842": {
        "data": false
    },
    "4797917826967671": {
        "data": false
    },
    "100049206701051": {
        "data": false
    },
    "100040169147705": {
        "data": false
    },
    "100073571006429": {
        "data": false
    },
    "100060842475971": {
        "data": false
    },
    "100033910325799": {
        "data": false
    },
    "100066713018556": {
        "data": false
    },
    "100058757077380": {
        "data": false
    },
    "5742394502456476": {
        "data": false
    },
    "8038684822812063": {
        "data": false
    },
    "100008374389509": {
        "data": false
    },
    "100081171075382": {
        "data": false
    },
    "100047577211803": {
        "data": false
    },
    "5825085107505836": {
        "data": false
    },
    "7403968883010457": {
        "data": false
    },
    "7784477721592224": {
        "data": false
    },
    "7900729736619575": {
        "data": true
    },
    "5460119494021831": {
        "data": true
    },
    "5036306543091456": {
        "data": false
    },
    "7663794486971969": {
        "data": false
    },
    "8240717212620769": {
        "data": false
    },
    "4921806091241943": {
        "data": false
    },
    "4933640980096699": {
        "data": false
    },
    "6065618296843513": {
        "data": false
    },
    "4849143655206531": {
        "data": false
    },
    "5137491196300238": {
        "data": false
    },
    "5431287580237064": {
        "data": false
    },
    "4853893041400316": {
        "data": false
    },
    "5150399155076288": {
        "data": false
    },
    "100028459110861": {
        "data": false
    },
    "5310283702393900": {
        "data": false
    },
    "100070521125386": {
        "data": false
    },
    "5048016351942779": {
        "data": false
    },
    "5201594803227606": {
        "data": false
    },
    "100057735612451": {
        "data": false
    },
    "4905097886285374": {
        "data": false
    },
    "100054827949220": {
        "data": false
    },
    "100081213574936": {
        "data": false
    },
    "7500677193307265": {
        "data": false
    },
    "5460552113964306": {
        "data": false
    },
    "5105861776201215": {
        "data": false
    },
    "4987680357997548": {
        "data": false
    },
    "5296565363733734": {
        "data": false
    },
    "5210028522369597": {
        "data": false
    },
    "5417882368246130": {
        "data": false
    },
    "4893764144050711": {
        "data": false
    },
    "5357777320911999": {
        "data": false
    },
    "4210817425710030": {
        "data": false
    },
    "4828988343857488": {
        "data": false
    },
    "5385926024774314": {
        "data": false
    },
    "4255307041236390": {
        "data": false
    },
    "5366634213376049": {
        "data": false
    },
    "5206004656142824": {
        "data": false
    },
    "100002326790705": {
        "data": false
    },
    "7440906129315861": {
        "data": false
    },
    "100042220763171": {
        "data": false
    },
    "5323449924361168": {
        "data": false
    },
    "4999318863478926": {
        "data": false
    },
    "5468838923139657": {
        "data": false
    },
    "5491864480845295": {
        "data": false
    },
    "7642729565797883": {
        "data": false
    },
    "7966137006761803": {
        "data": false
    },
    "4655024741247173": {
        "data": false
    },
    "5275849875806247": {
        "data": false
    },
    "5500153586718779": {
        "data": false
    },
    "6856902394382728": {
        "data": false
    },
    "5407908922555467": {
        "data": false
    },
    "7925893350757752": {
        "data": false
    },
    "5089422314487886": {
        "data": false
    },
    "4984040011677700": {
        "data": false
    },
    "4905256262825923": {
        "data": false
    },
    "4684906931618632": {
        "data": false
    },
    "7538735716197868": {
        "data": false
    },
    "5066140550120099": {
        "data": false
    },
    "4655225194575014": {
        "data": false
    },
    "7884190554925219": {
        "data": false
    },
    "4797384846997149": {
        "data": false
    },
    "5518891888205088": {
        "data": false
    },
    "7093435234061917": {
        "data": false
    },
    "7924753847550395": {
        "data": false
    },
    "7789890304370431": {
        "data": false
    },
    "5221144751264455": {
        "data": false
    },
    "100001631702617": {
        "data": false
    },
    "5896320813718436": {
        "data": false
    },
    "100040984926932": {
        "data": false
    },
    "100047083659561": {
        "data": false
    },
    "5115452951877288": {
        "data": false
    },
    "7467648826643864": {
        "data": false
    },
    "5141634302556274": {
        "data": false
    },
    "100049330453784": {
        "data": false
    },
    "100057310369331": {
        "data": false
    },
    "5011946445552572": {
        "data": false
    },
    "5627328297295824": {
        "data": false
    },
    "100028009914363": {
        "data": false
    },
    "100042552814104": {
        "data": false
    },
    "5476444469102862": {
        "data": false
    },
    "5586766511347935": {
        "data": false
    },
    "5355663287833372": {
        "data": false
    },
    "5093006697462187": {
        "data": false
    },
    "7798513750188837": {
        "data": false
    },
    "5511037938940445": {
        "data": false
    },
    "5123090861113809": {
        "data": false
    },
    "5700800229950007": {
        "data": false
    },
    "3663887693712634": {
        "data": false
    },
    "4841845462604027": {
        "data": false
    },
    "6912008908809280": {
        "data": false
    },
    "4220640381319915": {
        "data": false
    },
    "4840750052675027": {
        "data": false
    },
    "5185769734812028": {
        "data": false
    },
    "4334344213354439": {
        "data": false
    },
    "8022191501131915": {
        "data": false
    },
    "4999795010131907": {
        "data": false
    },
    "5029741257080069": {
        "data": false
    },
    "5849303375096451": {
        "data": false
    },
    "100002637836730": {
        "data": false
    },
    "5091876710905417": {
        "data": false
    },
    "100047993302072": {
        "data": false
    },
    "100075441617322": {
        "data": false
    },
    "7353013124768837": {
        "data": false
    },
    "5070070733070977": {
        "data": false
    },
    "5646051495428362": {
        "data": false
    },
    "3356449621079983": {
        "data": false
    },
    "5495410700489939": {
        "data": false
    },
    "5304765466257055": {
        "data": false
    },
    "5222138077821825": {
        "data": false
    },
    "100078300973176": {
        "data": false
    },
    "7464125173662295": {
        "data": false
    },
    "100036576590462": {
        "data": false
    },
    "100012842321236": {
        "data": false
    },
    "100052958136863": {
        "data": false
    },
    "100082581614277": {
        "data": false
    },
    "100075596391739": {
        "data": false
    },
    "100039620811888": {
        "data": false
    },
    "100023776313222": {
        "data": false
    },
    "100063481699880": {
        "data": false
    },
    "5288298361230511": {
        "data": false
    },
    "5357824514276971": {
        "data": false
    },
    "4551460124948936": {
        "data": false
    },
    "3699044686886436": {
        "data": false
    },
    "5052170358237112": {
        "data": false
    },
    "7717657834918324": {
        "data": false
    },
    "5218934368165811": {
        "data": false
    },
    "100082564403715": {
        "data": false
    },
    "5234586209962676": {
        "data": false
    },
    "7178677028869504": {
        "data": false
    },
    "4854615797938296": {
        "data": false
    },
    "100068437002675": {
        "data": false
    },
    "100007211387094": {
        "data": false
    },
    "4922427567861034": {
        "data": false
    },
    "100056740219661": {
        "data": false
    },
    "5225083547572865": {
        "data": false
    },
    "100075779328551": {
        "data": false
    },
    "100069189200809": {
        "data": false
    },
    "100033751985199": {
        "data": false
    },
    "100024471766168": {
        "data": false
    },
    "100048179379266": {
        "data": false
    },
    "5220678198017964": {
        "data": false
    },
    "5382608261799213": {
        "data": false
    },
    "5301688053185270": {
        "data": false
    },
    "5108249919273087": {
        "data": false
    },
    "5327429657273756": {
        "data": false
    },
    "100061424566402": {
        "data": false
    },
    "100071613866564": {
        "data": false
    },
    "100066901757246": {
        "data": false
    },
    "100064590017471": {
        "data": false
    },
    "100068031693006": {
        "data": false
    },
    "100065902906367": {
        "data": false
    },
    "5099701173412851": {
        "data": false
    },
    "5859637244052697": {
        "data": false
    },
    "5083271741756148": {
        "data": false
    },
    "5174455765977599": {
        "data": false
    },
    "5316350415052311": {
        "data": false
    },
    "5557480040950309": {
        "data": false
    },
    "100082724798253": {
        "data": false
    },
    "100070240246476": {
        "data": false
    },
    "5023429647765967": {
        "data": false
    },
    "4519869831391048": {
        "data": false
    },
    "5256732494362707": {
        "data": false
    },
    "5134029970024312": {
        "data": false
    },
    "7771983422842667": {
        "data": false
    },
    "100013256132391": {
        "data": false
    },
    "5528502220517337": {
        "data": false
    },
    "100068109231699": {
        "data": false
    },
    "100011712397942": {
        "data": false
    },
    "100009815106119": {
        "data": false
    },
    "100042511171399": {
        "data": false
    },
    "100082234812595": {
        "data": false
    },
    "100069807585262": {
        "data": false
    },
    "4765827053500194": {
        "data": false
    },
    "100082854439144": {
        "data": false
    },
    "100036852192018": {
        "data": false
    },
    "5129398363762985": {
        "data": false
    },
    "5152069734909866": {
        "data": false
    },
    "5616752391681032": {
        "data": false
    },
    "100081843844003": {
        "data": false
    },
    "100050239662261": {
        "data": false
    },
    "100016760731225": {
        "data": false
    },
    "5466141863446030": {
        "data": false
    },
    "3656910244384191": {
        "data": false
    },
    "7728065197263994": {
        "data": false
    },
    "100077482489224": {
        "data": false
    },
    "5654336167944110": {
        "data": false
    },
    "5256786857721906": {
        "data": false
    },
    "5339351309490265": {
        "data": false
    },
    "100071614268027": {
        "data": false
    },
    "6023223371026649": {
        "data": false
    },
    "100022224793054": {
        "data": false
    },
    "5334735166609896": {
        "data": false
    },
    "5255206167891264": {
        "data": false
    },
    "6656280914414441": {
        "data": false
    },
    "5543132195696770": {
        "data": false
    },
    "100051401016183": {
        "data": false
    },
    "5771960099505390": {
        "data": false
    },
    "5273910322723369": {
        "data": false
    },
    "5282325455155337": {
        "data": false
    },
    "8123111201039799": {
        "data": false
    },
    "7572878769419776": {
        "data": false
    },
    "5899091286785055": {
        "data": false
    },
    "5705337896144330": {
        "data": false
    },
    "100072956762645": {
        "data": false
    },
    "7876393655734070": {
        "data": false
    },
    "7696713540403243": {
        "data": false
    },
    "5321313117986915": {
        "data": false
    },
    "5113792952066969": {
        "data": false
    },
    "7831152536956062": {
        "data": false
    },
    "100072942274444": {
        "data": false
    },
    "100052973151147": {
        "data": false
    },
    "100064289821916": {
        "data": false
    },
    "5213305898706655": {
        "data": false
    },
    "100054604536498": {
        "data": false
    },
    "7691907790851422": {
        "data": false
    },
    "5229182793836038": {
        "data": false
    },
    "100005263830215": {
        "data": false
    },
    "100055054862251": {
        "data": false
    },
    "5694666713898819": {
        "data": false
    },
    "5066104410111210": {
        "data": false
    },
    "4587143898054971": {
        "data": false
    },
    "100047152010637": {
        "data": false
    },
    "100076440455636": {
        "data": false
    },
    "100067548053645": {
        "data": false
    },
    "100050803900457": {
        "data": false
    },
    "5290101834437540": {
        "data": false
    },
    "5290840524364747": {
        "data": false
    },
    "7690066277733461": {
        "data": false
    },
    "8477008882325038": {
        "data": false
    },
    "4710243662408819": {
        "data": false
    },
    "4182117001838004": {
        "data": false
    },
    "100006895238093": {
        "data": false
    },
    "5260395854010544": {
        "data": false
    },
    "4813606645415265": {
        "data": false
    },
    "3877976358969927": {
        "data": false
    },
    "100028520805606": {
        "data": false
    },
    "5107292286055702": {
        "data": false
    },
    "3972582586200409": {
        "data": false
    },
    "5012979782164678": {
        "data": false
    },
    "4803907306344987": {
        "data": false
    },
    "5113651218701753": {
        "data": false
    },
    "4557888514316652": {
        "data": false
    },
    "5751656451558018": {
        "data": false
    },
    "5162647450518077": {
        "data": false
    },
    "4792731360780917": {
        "data": false
    },
    "8020651864619087": {
        "data": false
    },
    "5018398464937044": {
        "data": false
    },
    "5498281953516743": {
        "data": false
    },
    "3993063614038498": {
        "data": false
    },
    "5346682558732525": {
        "data": false
    },
    "7655599977845339": {
        "data": false
    },
    "7877816508925930": {
        "data": false
    },
    "4837707342997859": {
        "data": false
    },
    "5391382767579674": {
        "data": false
    },
    "5827938030555955": {
        "data": false
    },
    "4948665321927203": {
        "data": false
    },
    "7421363501269483": {
        "data": false
    },
    "5168368356615682": {
        "data": false
    },
    "5076275165823448": {
        "data": false
    },
    "4741831302581930": {
        "data": false
    },
    "5266316856756654": {
        "data": false
    },
    "5129376730516547": {
        "data": false
    },
    "7996136530428908": {
        "data": false
    },
    "7128146793894262": {
        "data": false
    },
    "5096738083746478": {
        "data": false
    },
    "5913778565338894": {
        "data": false
    },
    "5085405464886303": {
        "data": false
    },
    "100000205086898": {
        "data": false
    },
    "100050244725622": {
        "data": false
    },
    "5092964074151492": {
        "data": false
    },
    "5515963735116853": {
        "data": false
    },
    "5150585554977172": {
        "data": false
    },
    "6043189329028945": {
        "data": false
    },
    "5892967364065609": {
        "data": false
    },
    "100077150056585": {
        "data": false
    },
    "5249106605144616": {
        "data": false
    },
    "8400774679936202": {
        "data": false
    },
    "5325827030835561": {
        "data": false
    },
    "7406254906081499": {
        "data": false
    },
    "5380490985333224": {
        "data": false
    },
    "7721462987926903": {
        "data": false
    },
    "5728461650498576": {
        "data": false
    },
    "5854643991232043": {
        "data": false
    },
    "4930023897124698": {
        "data": false
    },
    "4842830042487840": {
        "data": false
    },
    "5380658861980333": {
        "data": false
    },
    "5614172871948506": {
        "data": false
    },
    "5236024909780696": {
        "data": false
    },
    "5598851453517655": {
        "data": false
    },
    "7647532321955909": {
        "data": false
    },
    "2679344562119896": {
        "data": false
    },
    "100073404638767": {
        "data": false
    },
    "6005019702846554": {
        "data": false
    },
    "100010434151707": {
        "data": false
    },
    "4716503275113243": {
        "data": false
    },
    "5833530066666894": {
        "data": false
    },
    "100000272507589": {
        "data": false
    },
    "100073938045680": {
        "data": false
    },
    "100083808553681": {
        "data": false
    },
    "5313198792096534": {
        "data": false
    },
    "100078797109741": {
        "data": false
    },
    "100078155328734": {
        "data": false
    },
    "5254852667924376": {
        "data": false
    },
    "100070277082412": {
        "data": false
    },
    "100047619517754": {
        "data": false
    },
    "100066674777332": {
        "data": false
    },
    "4551411774906387": {
        "data": false
    },
    "100046325164874": {
        "data": false
    },
    "7827549783982715": {
        "data": false
    },
    "100001388612996": {
        "data": false
    },
    "7540372846033191": {
        "data": false
    },
    "5981286538548692": {
        "data": false
    },
    "7843304512408288": {
        "data": false
    },
    "100034600056486": {
        "data": false
    },
    "100054563574195": {
        "data": false
    },
    "5039151512788628": {
        "data": false
    },
    "5532145830169046": {
        "data": false
    },
    "7833013596739558": {
        "data": false
    },
    "5306857272742963": {
        "data": false
    },
    "7813056802100539": {
        "data": false
    },
    "5508082419212153": {
        "data": false
    },
    "100052420069873": {
        "data": false
    },
    "100071084504201": {
        "data": false
    },
    "5275725519140564": {
        "data": false
    },
    "5412474405497327": {
        "data": false
    },
    "4854553864651195": {
        "data": false
    },
    "100035215631263": {
        "data": false
    },
    "8461726577178121": {
        "data": false
    },
    "100077023665191": {
        "data": false
    },
    "100067506304360": {
        "data": false
    },
    "5743086872370064": {
        "data": false
    },
    "100080960521447": {
        "data": false
    },
    "100020002516099": {
        "data": false
    },
    "100056681359681": {
        "data": false
    },
    "4355796504517666": {
        "data": false
    },
    "100054870732307": {
        "data": false
    },
    "100079128506325": {
        "data": false
    },
    "5269759949809775": {
        "data": false
    },
    "8328468607178685": {
        "data": false
    },
    "5558074927546120": {
        "data": false
    },
    "5496871797046821": {
        "data": false
    },
    "100060465465854": {
        "data": false
    },
    "100061167043906": {
        "data": false
    },
    "100084208654884": {
        "data": false
    },
    "5448550471896132": {
        "data": false
    },
    "5500875746602077": {
        "data": false
    },
    "5215965521785090": {
        "data": false
    },
    "4669040276537828": {
        "data": false
    },
    "5734800889872824": {
        "data": false
    },
    "100067361465049": {
        "data": false
    },
    "100037329122064": {
        "data": false
    },
    "7702716356467666": {
        "data": false
    },
    "100074718007607": {
        "data": false
    },
    "100065531349388": {
        "data": false
    },
    "100072215785427": {
        "data": false
    },
    "8373231552690677": {
        "data": false
    },
    "5281016918640767": {
        "data": false
    },
    "5268222293214222": {
        "data": false
    },
    "100039885470685": {
        "data": false
    },
    "100070756235161": {
        "data": false
    },
    "5367437993353876": {
        "data": false
    },
    "7788810697856894": {
        "data": false
    },
    "5298370746925951": {
        "data": false
    },
    "100084035917282": {
        "data": false
    },
    "5145470328873791": {
        "data": false
    },
    "5321532434620712": {
        "data": false
    },
    "100079029894039": {
        "data": false
    },
    "100022173704200": {
        "data": false
    },
    "5329411260469974": {
        "data": false
    },
    "4857338467704952": {
        "data": false
    },
    "100079089161669": {
        "data": false
    },
    "7709047895832628": {
        "data": false
    },
    "5449148521790774": {
        "data": false
    },
    "5280689395351389": {
        "data": false
    },
    "5504064119657506": {
        "data": false
    },
    "4974683719321548": {
        "data": false
    },
    "5325608667560155": {
        "data": false
    },
    "5700763219936760": {
        "data": false
    },
    "100055761352485": {
        "data": false
    },
    "100010557968992": {
        "data": false
    },
    "6278089192206646": {
        "data": false
    },
    "5376543409078009": {
        "data": false
    },
    "100074379105706": {
        "data": false
    },
    "5352892414798947": {
        "data": false
    },
    "4756724827760841": {
        "data": false
    },
    "100030628008904": {
        "data": false
    },
    "100050226382571": {
        "data": false
    },
    "100055671130965": {
        "data": false
    },
    "7648893431847468": {
        "data": false
    },
    "6021328887880557": {
        "data": false
    },
    "5179478482087815": {
        "data": false
    },
    "100014737153946": {
        "data": false
    },
    "8199207350152511": {
        "data": false
    },
    "5265183076875437": {
        "data": false
    },
    "100058681505554": {
        "data": false
    },
    "5226014644093193": {
        "data": false
    },
    "5432348680152810": {
        "data": false
    },
    "5029377913827673": {
        "data": false
    },
    "7775343629204054": {
        "data": false
    },
    "4989242451185406": {
        "data": false
    },
    "5402359419802163": {
        "data": false
    },
    "5372029769499590": {
        "data": false
    },
    "4673317922771567": {
        "data": false
    },
    "100000321332736": {
        "data": false
    },
    "5670081106337036": {
        "data": false
    },
    "100083965503178": {
        "data": false
    },
    "5072225562832472": {
        "data": false
    },
    "100057833711440": {
        "data": false
    },
    "5463437040368596": {
        "data": false
    },
    "4916676188433501": {
        "data": false
    },
    "5387666914673665": {
        "data": false
    },
    "5551947768195235": {
        "data": false
    },
    "4607507662708588": {
        "data": false
    },
    "7969557989786167": {
        "data": false
    },
    "7934726003236579": {
        "data": false
    },
    "5626285427466042": {
        "data": false
    },
    "100082787058377": {
        "data": false
    },
    "5841508349246336": {
        "data": false
    },
    "5253494998013794": {
        "data": false
    },
    "100082873819830": {
        "data": false
    },
    "4194237324034801": {
        "data": false
    },
    "100073563635888": {
        "data": false
    },
    "8212619712145093": {
        "data": false
    },
    "8074224472649716": {
        "data": false
    },
    "4927322824044304": {
        "data": false
    },
    "5134664269993122": {
        "data": false
    },
    "5357301604383262": {
        "data": false
    },
    "5712011568833774": {
        "data": false
    },
    "5423422921054521": {
        "data": false
    },
    "5960104560666895": {
        "data": false
    }
}